TorchSUL/Base.py
TorchSUL/DataReader.py
TorchSUL/Layers.py
TorchSUL/Model.py
TorchSUL/Quant.py
TorchSUL/__init__.py
TorchSUL/sul_tool.py
TorchSUL/sulio.py
TorchSUL/sulplotter.py
TorchSUL-0.1.29.dist-info/METADATA
TorchSUL-0.1.29.dist-info/WHEEL
TorchSUL-0.1.29.dist-info/top_level.txt
TorchSUL-0.1.29.dist-info/RECORD
