Metadata-Version: 2.1
Name: TorchSUL
Version: 0.1.29
Summary: Simple but useful layers for Pytorch
Home-page: https://github.com/ddddwee1/TorchSUL
Author: Cheng Yu
Author-email: chengyu996@gmail.com
Requires-Dist: tqdm
Requires-Dist: progressbar2
Requires-Dist: opencv-python
Requires-Dist: matplotlib
